ML_TheBridge/__init__.py
ML_TheBridge/functions.py
ML_TheBridge-0.0.0.dist-info/LICENSE.txt
ML_TheBridge-0.0.0.dist-info/METADATA
ML_TheBridge-0.0.0.dist-info/WHEEL
ML_TheBridge-0.0.0.dist-info/top_level.txt
ML_TheBridge-0.0.0.dist-info/RECORD
